py_lockfile.py
py_lockfile2-0.5.0.dist-info/LICENSE
py_lockfile2-0.5.0.dist-info/METADATA
py_lockfile2-0.5.0.dist-info/WHEEL
py_lockfile2-0.5.0.dist-info/entry_points.txt
py_lockfile2-0.5.0.dist-info/RECORD
